langsmith_tool_server/__init__.py
langsmith_tool_server/_version.py
langsmith_tool_server/context.py
langsmith_tool_server/mcp.py
langsmith_tool_server/mcp_loader.py
langsmith_tool_server/root.py
langsmith_tool_server/splash.py
langsmith_tool_server/tool.py
langsmith_tool_server/tools.py
langsmith_tool_server/auth/__init__.py
langsmith_tool_server/auth/exceptions.py
langsmith_tool_server/auth/middleware.py
langsmith_tool_server/auth/types.py
langsmith_tool_server-0.2.8.dist-info/METADATA
langsmith_tool_server-0.2.8.dist-info/WHEEL
langsmith_tool_server-0.2.8.dist-info/RECORD
